README.md
setup.cfg
setup.py
src/genesiscloud/__init__.py
src/genesiscloud/client.py
src/py_genesiscloud.egg-info/PKG-INFO
src/py_genesiscloud.egg-info/SOURCES.txt
src/py_genesiscloud.egg-info/dependency_links.txt
src/py_genesiscloud.egg-info/not-zip-safe
src/py_genesiscloud.egg-info/requires.txt
src/py_genesiscloud.egg-info/top_level.txt