Metadata-Version: 2.1
Name: py-genesiscloud
Version: 0.2.1
Summary: A library to interact with genesiscloud
Home-page: https://github.com/genesiscloud/py-genesiscloud
Author: GenesisCloud
Author-email: opensource@genesiscloud.com
License: UNKNOWN
Platform: UNKNOWN
Classifier: Programming Language :: Python :: 3
Classifier: License :: OSI Approved :: MIT License
Classifier: Operating System :: OS Independent
Classifier: Development Status :: 4 - Beta
Classifier: Environment :: GPU
Classifier: Intended Audience :: Information Technology
Classifier: Intended Audience :: Developers
Classifier: License :: OSI Approved :: MIT License
Requires-Python: >=3.6
Provides-Extra: test
Provides-Extra: dev
